sinricpro/__init__.py
sinricpro/capabilities/__init__.py
sinricpro/capabilities/air_quality_sensor.py
sinricpro/capabilities/brightness_controller.py
sinricpro/capabilities/camera_controller.py
sinricpro/capabilities/channel_controller.py
sinricpro/capabilities/color_controller.py
sinricpro/capabilities/color_temperature_controller.py
sinricpro/capabilities/contact_sensor.py
sinricpro/capabilities/equalizer_controller.py
sinricpro/capabilities/input_controller.py
sinricpro/capabilities/lock_controller.py
sinricpro/capabilities/media_controller.py
sinricpro/capabilities/mode_controller.py
sinricpro/capabilities/motion_sensor.py
sinricpro/capabilities/mute_controller.py
sinricpro/capabilities/open_close_controller.py
sinricpro/capabilities/percentage_controller.py
sinricpro/capabilities/power_level_controller.py
sinricpro/capabilities/power_sensor.py
sinricpro/capabilities/power_state_controller.py
sinricpro/capabilities/push_notification.py
sinricpro/capabilities/range_controller.py
sinricpro/capabilities/setting_controller.py
sinricpro/capabilities/temperature_sensor.py
sinricpro/capabilities/thermostat_controller.py
sinricpro/capabilities/volume_controller.py
sinricpro/core/__init__.py
sinricpro/core/actions.py
sinricpro/core/event_limiter.py
sinricpro/core/exceptions.py
sinricpro/core/message_queue.py
sinricpro/core/signature.py
sinricpro/core/sinric_pro.py
sinricpro/core/sinric_pro_device.py
sinricpro/core/types.py
sinricpro/core/websocket_client.py
sinricpro/devices/__init__.py
sinricpro/devices/sinric_pro_air_quality_sensor.py
sinricpro/devices/sinric_pro_blinds.py
sinricpro/devices/sinric_pro_camera.py
sinricpro/devices/sinric_pro_contact_sensor.py
sinricpro/devices/sinric_pro_custom_device.py
sinricpro/devices/sinric_pro_dimswitch.py
sinricpro/devices/sinric_pro_doorbell.py
sinricpro/devices/sinric_pro_fan.py
sinricpro/devices/sinric_pro_garage_door.py
sinricpro/devices/sinric_pro_light.py
sinricpro/devices/sinric_pro_lock.py
sinricpro-5.0.1.dist-info/licenses/LICENSE
sinricpro-5.0.1.dist-info/METADATA
sinricpro-5.0.1.dist-info/WHEEL
sinricpro-5.0.1.dist-info/top_level.txt
sinricpro-5.0.1.dist-info/RECORD
