Metadata-Version: 2.4
Name: sinricpro
Version: 5.0.1
Summary: Official SinricPro SDK for Python - Control IoT devices with Alexa and Google Home
Author-email: SinricPro <support@sinric.pro>
License: CC-BY-SA-4.0
Project-URL: Homepage, https://sinric.pro
Project-URL: Repository, https://github.com/sinricpro/python-sdk
Project-URL: Issues, https://github.com/sinricpro/python-sdk/issues
Project-URL: Documentation, https://sinric.pro/python-sdk-docs
Keywords: sinricpro,alexa,google-home,smart-home,iot,websocket,home-automation
Classifier: Development Status :: 4 - Beta
Classifier: Intended Audience :: Developers
Classifier: Topic :: Home Automation
Classifier: Topic :: Software Development :: Libraries :: Python Modules
Classifier: License :: Free For Educational Use
Classifier: Programming Language :: Python :: 3
Classifier: Programming Language :: Python :: 3.10
Classifier: Programming Language :: Python :: 3.11
Classifier: Programming Language :: Python :: 3.12
Classifier: Operating System :: OS Independent
Requires-Python: >=3.10
License-File: LICENSE
Requires-Dist: websockets>=12.0
Requires-Dist: aiohttp>=3.9.0
Provides-Extra: dev
Requires-Dist: pytest>=7.0; extra == "dev"
Requires-Dist: pytest-asyncio>=0.21; extra == "dev"
Requires-Dist: pytest-cov>=4.0; extra == "dev"
Requires-Dist: black>=23.0; extra == "dev"
Requires-Dist: flake8>=6.0; extra == "dev"
Requires-Dist: mypy>=1.0; extra == "dev"
Requires-Dist: isort>=5.12; extra == "dev"
Dynamic: license-file
